libsid/__init__.py
libsid/test.py
libsid/camera/__init__.py
libsid/camera/camera.py
libsid/camera/converstions.py
libsid/demo/__init__.py
libsid/demo/arctic_helper.py
libsid/demo/arctic_open3d.py
libsid/demo/arctic_pytorch3d.py
libsid/visualise/Open3dVis.py
libsid/visualise/Pytorch3dVis.py
libsid/visualise/__init__.py
libsid-0.0.1.dist-info/METADATA
libsid-0.0.1.dist-info/WHEEL
libsid-0.0.1.dist-info/top_level.txt
libsid-0.0.1.dist-info/RECORD
